README.md
setup.py
jsonschema_typed/__init__.py
jsonschema_typed/plugin.py
jsonschema_typed/types.py
jsonschema_typed2.egg-info/PKG-INFO
jsonschema_typed2.egg-info/SOURCES.txt
jsonschema_typed2.egg-info/dependency_links.txt
jsonschema_typed2.egg-info/not-zip-safe
jsonschema_typed2.egg-info/requires.txt
jsonschema_typed2.egg-info/top_level.txt