Metadata-Version: 2.1
Name: jsonschema-typed2
Version: 0.1.0
Summary: UNKNOWN
Home-page: https://github.com/connorworley/jsonschema-typed
Author: Connor Worley
Author-email: connorbworley@gmail.com
License: MIT
Platform: UNKNOWN
Requires-Python: ~=3.6
